my_module/__init__.py
my_module/used_mp.py
use_mp_tta-1.0.3.dist-info/LICENSE.txt
use_mp_tta-1.0.3.dist-info/METADATA
use_mp_tta-1.0.3.dist-info/WHEEL
use_mp_tta-1.0.3.dist-info/top_level.txt
use_mp_tta-1.0.3.dist-info/RECORD
