Metadata-Version: 2.1
Name: use-mp-tta
Version: 1.0.3
Summary: init TTA_prepro_Data_method
Home-page: https://github.com/ParkHwan/create_module
Author: TTA_DE_PH
Author-email: kanjanggun@naver.com
License: MIT
Project-URL: Bug Tracker, https://github.com/ParkHwan/create_module/issues
Classifier: Programming Language :: Python :: 3
Classifier: License :: OSI Approved :: MIT License
Requires-Python: >=3
License-File: LICENSE.txt
Requires-Dist: boto3 >=1.24.28
Requires-Dist: smart-open >=6.2.0
